brainweb/__init__.py
brainweb/utils.py
brainweb-1.6.2.dist-info/METADATA
brainweb-1.6.2.dist-info/WHEEL
brainweb-1.6.2.dist-info/top_level.txt
brainweb-1.6.2.dist-info/RECORD
