Metadata-Version: 2.1
Name: brainweb
Version: 1.6.2
Summary: BrainWeb-based multimodal models of 20 normal brains
Home-page: https://github.com/casperdcl/brainweb
Author: Casper da Costa-Luis
Author-email: casper.dcl@physics.org
License: MPLv2.0
Keywords: pet-mr,volume-rendering,neuroimaging,fdg,mri
Platform: any
Classifier: Development Status :: 4 - Beta
Classifier: Framework :: IPython
Classifier: License :: OSI Approved :: Mozilla Public License 2.0 (MPL 2.0)
Classifier: Programming Language :: Python
Classifier: Programming Language :: Python :: 2
Classifier: Programming Language :: Python :: 3
Requires-Dist: tqdm (>=4.42.0)
Requires-Dist: requests
Requires-Dist: numpy
Requires-Dist: scikit-image
Provides-Extra: plot
Requires-Dist: matplotlib ; extra == 'plot'
Provides-Extra: register
Requires-Dist: dipy ; extra == 'register'
Provides-Extra: test
Requires-Dist: docutils ; extra == 'test'
Requires-Dist: pygments ; extra == 'test'
Requires-Dist: flake8 ; extra == 'test'
